noroot_ping-0.1.1.dist-info/METADATA
noroot_ping-0.1.1.dist-info/WHEEL
noroot_ping/__init__.py
noroot_ping/noroot_ping.cpython-311-x86_64-linux-gnu.so
noroot_ping-0.1.1.dist-info/RECORD
